mastercard_match-1.0.5.dist-info/DESCRIPTION.rst
mastercard_match-1.0.5.dist-info/METADATA
mastercard_match-1.0.5.dist-info/RECORD
mastercard_match-1.0.5.dist-info/WHEEL
mastercard_match-1.0.5.dist-info/metadata.json
mastercard_match-1.0.5.dist-info/top_level.txt
mastercardmatch/__init__.py
mastercardmatch/acquirercontactrequest.py
mastercardmatch/addterminatedmerchant.py
mastercardmatch/resourceconfig.py
mastercardmatch/retroactiveinquirydetailsrequest.py
mastercardmatch/retroactiveinquiryrequest.py
mastercardmatch/terminationinquiryhistoryrequest.py
mastercardmatch/terminationinquiryrequest.py
